DAY_1/design.sv
// Code your design here
`timescale 1ns / 1ps 
module full_adder( A, B, Cin, S, Cout);

 input wire A, B, Cin;
 output reg S, Cout;

 always @(A or B or Cin)
  begin 
   S = A ^ B ^ Cin; 
   Cout = A&B | (A^B) & Cin; 
  end
endmodule

DAY_1/testbench.sv
// Code your testbench here
// or browse Examples
`timescale 1ns / 1ps
module DUT;

  //declare testbench variables
  reg  A_input, B_input, C_input;
  wire Sum, C_output;  

 //instantiate the design module and connect to the testbench variables
  full_adder instantiation(.A(A_input), .B(B_input), .Cin(C_input), .S(Sum), .Cout(C_output));

  initial
    begin
      $dumpfile("xyz.vcd");
      $dumpvars;

      //set stimulus to test the code
      A_input=0;
      B_input=0;
      C_input=0;
       #100 $finish;
    end

//provide the toggling input (just like truth table input)
//this acts as the clock input
always #40 A_input=~A_input;
always #20 B_input=~B_input;
always #10 C_input=~C_input;

//display output if there’s a change in the input event
  always @(A_input or B_input or C_input)
      $monitor("At TIME(in ns)=%t, A=%d B=%d C=%d Sum = %d Carry = %d", $time, A_input, B_input, C_input, Sum, C_output);

endmodule

DAY_1/xyz.vcd
$date
	Thu Apr 20 14:32:51 2023
$end
$version
	Icarus Verilog
$end
$timescale
	1ps
$end
$scope module DUT $end
$var wire 1 ! C_output $end
$var wire 1 " Sum $end
$var reg 1 # A_input $end
$var reg 1 $ B_input $end
$var reg 1 % C_input $end
$scope module instantiation $end
$var wire 1 & A $end
$var wire 1 ' B $end
$var wire 1 ( Cin $end
$var reg 1 ) Cout $end
$var reg 1 * S $end
$upscope $end
$upscope $end
$enddefinitions $end
#0
$dumpvars
0*
0)
0(
0'
0&
0%
0$
0#
0"
0!
$end
#10000
1*
1"
1%
1(
#20000
0%
0(
1$
1'
#30000
1)
1!
0*
0"
1%
1(
#40000
0)
0!
1*
1"
0%
0(
0$
0'
1#
1&
#50000
1)
1!
0*
0"
1%
1(
#60000
0%
0(
1$
1'
#70000
1*
1"
1%
1(
#80000
0)
0!
0*
0"
0%
0(
0$
0'
0#
0&
#90000
1*
1"
1%
1(
#100000
0%
0(
1$
1'
