DAY_21/design.sv
`timescale 10ns/1ps

module SR_latch(input E,R,S, 
                output Q,Qbar); 
  
  wire R_TEMP, S_TEMP;

  nand(R_TEMP,R,E);
  nand(S_TEMP,S,E);
  nand (Qbar, R_TEMP, Q); 
  nand(Q, S_TEMP, Qbar); 
  
endmodule

DAY_21/testbench.sv
`timescale 10ns/1ps

module SR_LATCH_TB;

reg R, S, E;
wire Q, Qbar;

  SR_latch DUT(E,R,S,Q,Qbar);

initial
  begin
    $dumpfile("dump.vcd");
    $dumpvars(1);
    
    R=1'b0;
    S=1'b0;
    
   
    E=1'b1;
    
#5  S=1'b1;
#5  S=1'b0;
#5  R=1'b1;
#5  R=1'b0;
    
    E=1'b0;
    
#5  S=1'b1;
#5  S=1'b0;
#5  R=1'b1;
#5  R=1'b0;
#5  $finish;
  end
endmodule

DAY_21/dump.vcd
$date
    May 22, 2023  12:49:15
$end
$version
    TOOL:	xmsim	20.09-s003
$end
$timescale
    1 ps
$end

$scope module SR_LATCH_TB $end
$var reg       1 !    R $end
$var reg       1 "    S $end
$var reg       1 #    E $end
$var wire      1 $    Q  $end
$var wire      1 %    Qbar  $end
$upscope $end

$enddefinitions $end
$dumpvars
0!
0"
1#
x$
x%
$end
#50000
1"
1$
0%
#100000
0"
#150000
1!
1%
0$
#200000
0!
0#
#250000
1"
#300000
0"
#350000
1!
#400000
0!
