DAY_29/design.sv
`timescale 10ns/1ps
module MOD_N_COUNTER #(parameter N=16,parameter WIDTH=4)
	        		(input clk,reset,
	        		 output reg [WIDTH-1:0] out
                    );

always@(posedge clk)
  
  begin
    if(!reset)
      out <= 0;
    else
      if(out == N-1)
        out <= 0;
    else
      out <= out + 1;
  end              
endmodule

DAY_29/testbench.sv
`timescale 10ns/1ps
module MOD_N_COUNTER_TB;
	
  parameter N = 16;
  parameter WIDTH = 4;

  reg clk,reset;
  wire [WIDTH-1:0] out;

  MOD_N_COUNTER DUT(.clk(clk),
                    .reset(reset),
                    .out(out));
	        
always #5 clk = ~clk;
  
  initial
    begin
      clk=0;
      reset = 0;
      #15;
      reset = 1; 
      
      #200 $finish;
    end
  
  initial 
    begin
      $dumpfile("dump.vcd");
      $dumpvars;
    end
  
endmodule

DAY_29/dump.vcd
$date
	Fri Jun  9 01:36:42 2023
$end
$version
	QuestaSim Version 2021.3
$end
$timescale
	1ps
$end

$scope module MOD_N_COUNTER_TB $end
$var parameter 32 ! N $end
$var parameter 32 " WIDTH $end
$var reg 1 # clk $end
$var reg 1 $ reset $end
$var wire 1 % out [3] $end
$var wire 1 & out [2] $end
$var wire 1 ' out [1] $end
$var wire 1 ( out [0] $end

$scope module DUT $end
$var parameter 32 ) N $end
$var parameter 32 * WIDTH $end
$var wire 1 + clk $end
$var wire 1 , reset $end
$var reg 4 - out [3:0] $end
$upscope $end
$upscope $end

$scope begin std $end
$upscope $end
$enddefinitions $end
#0
$dumpvars
0#
0$
bx -
b10000 !
b100 "
b10000 )
b100 *
x(
x'
x&
x%
0,
0+
$end
#50000
1#
1+
b0 -
0(
0'
0&
0%
#100000
0#
0+
#150000
1$
1#
1,
1+
b1 -
1(
#200000
0#
0+
#250000
1#
1+
b10 -
0(
1'
#300000
0#
0+
#350000
1#
1+
b11 -
1(
#400000
0#
0+
#450000
1#
1+
b100 -
0(
0'
1&
#500000
0#
0+
#550000
1#
1+
b101 -
1(
#600000
0#
0+
#650000
1#
1+
b110 -
0(
1'
#700000
0#
0+
#750000
1#
1+
b111 -
1(
#800000
0#
0+
#850000
1#
1+
b1000 -
0(
0'
0&
1%
#900000
0#
0+
#950000
1#
1+
b1001 -
1(
#1000000
0#
0+
#1050000
1#
1+
b1010 -
0(
1'
#1100000
0#
0+
#1150000
1#
1+
b1011 -
1(
#1200000
0#
0+
#1250000
1#
1+
b1100 -
0(
0'
1&
#1300000
0#
0+
#1350000
1#
1+
b1101 -
1(
#1400000
0#
0+
#1450000
1#
1+
b1110 -
0(
1'
#1500000
0#
0+
#1550000
1#
1+
b1111 -
1(
#1600000
0#
0+
#1650000
1#
1+
b0 -
0(
0'
0&
0%
#1700000
0#
0+
#1750000
1#
1+
b1 -
1(
#1800000
0#
0+
#1850000
1#
1+
b10 -
0(
1'
#1900000
0#
0+
#1950000
1#
1+
b11 -
1(
#2000000
0#
0+
#2050000
1#
1+
b100 -
0(
0'
1&
