DAY_38/design.sv
module PIPO(
  			input clk,clr,
  			input [3:0] data_in,
  			output reg [3:0] data_out
			);

always @(posedge clk)
	begin
      if (clr)
      	data_out <= 4'b0000;
      else
      	data_out <= data_in;
    end
  
  
endmodule

DAY_38/testbench.sv
module PIPO_TB;

reg clk,clr;
reg [3:0] data_in;

wire [3:0] data_out;

PIPO DUT (clk,
             clr,
             data_in,
             data_out
            );

always #5 clk = ~clk;

initial 
  begin
      clk = 0;
      clr = 0;
      data_in = 0;

      #5 clr=1;
      #5 clr=0;

      #10 data_in=4'b1001;
      #10 data_in=4'b1010;
      #10 data_in=4'b1011;
      #10 data_in=4'b1110;
      #10 data_in=4'b1111;
      #10 data_in=4'b0000;
      #150 $finish;
  end



initial 
  begin
    $dumpfile("dump.vcd");
	$dumpvars;
  end 
  
  
  
  
endmodule

DAY_38/dump.vcd
$date
	Tue Jun 20 05:45:30 2023
$end
$version
	Icarus Verilog
$end
$timescale
	1s
$end
$scope module PIPO_TB $end
$var wire 4 ! data_out [3:0] $end
$var reg 1 " clk $end
$var reg 1 # clr $end
$var reg 4 $ data_in [3:0] $end
$scope module DUT $end
$var wire 1 % clk $end
$var wire 1 & clr $end
$var wire 4 ' data_in [3:0] $end
$var reg 4 ( data_out [3:0] $end
$upscope $end
$upscope $end
$enddefinitions $end
#0
$dumpvars
bx (
b0 '
0&
0%
b0 $
0#
0"
bx !
$end
#5
b0 (
b0 !
1#
1&
1"
1%
#10
0#
0&
0"
0%
#15
1"
1%
#20
0"
0%
b1001 $
b1001 '
#25
b1001 (
b1001 !
1"
1%
#30
0"
0%
b1010 $
b1010 '
#35
b1010 (
b1010 !
1"
1%
#40
0"
0%
b1011 $
b1011 '
#45
b1011 (
b1011 !
1"
1%
#50
0"
0%
b1110 $
b1110 '
#55
b1110 (
b1110 !
1"
1%
#60
0"
0%
b1111 $
b1111 '
#65
b1111 (
b1111 !
1"
1%
#70
0"
0%
b0 $
b0 '
#75
b0 (
b0 !
1"
1%
