DAY_26/design.sv
`timescale 10ns/1ps

module JK_ff(input J,K,clk,RST,
             output reg Q
             );
	
always@(posedge clk)
    begin
      if(RST)
        Q <= 1'b1;
      else  
        begin
        case({J,K})
          2'b00: Q <= Q;
          2'b01: Q <= 1'b0;
          2'b10: Q <= 1'b1;
          2'b11: Q <= ~Q;
        endcase
      end          
	end
endmodule
	
module async_4bit_count(input J,K,clk,RST,
                        output [3:0]q
                        );

    JK_ff JK1(J,K,clk,RST,q[0]);
	JK_ff JK2(J,K,q[0],RST,q[1]);
	JK_ff JK3(J,K,q[1],RST,q[2]);
	JK_ff JK4(J,K,q[2],RST,q[3]);
  
endmodule

DAY_26/testbench.sv
`timescale 10ns/1ps

module async_4bit_count_tb;
  
	reg J,K,clk,RST;
	wire [3:0]q;
  
  
async_4bit_count DUT(J,K,clk,RST,q);
  
initial 
	begin 
	  J<=1'b0;
	  K<=1'b0;
	  RST=1;
	  clk=0;
      $dumpfile("waves.vcd");
      $dumpvars;
      forever #5 clk=~clk;
	end
  
initial 
  begin
	#20 
	RST<=0;
	J<=1'b1;
	K<=1'b1;
	#160 RST=1;
	#20
	RST<=0;
	#20
	$finish;
  end
  
endmodule

DAY_26/waves.vcd
$date
	Tue May 30 13:41:39 2023
$end
$version
	Icarus Verilog
$end
$timescale
	1ps
$end
$scope module async_4bit_count_tb $end
$var wire 4 ! q [3:0] $end
$var reg 1 " J $end
$var reg 1 # K $end
$var reg 1 $ RST $end
$var reg 1 % clk $end
$scope module DUT $end
$var wire 1 & J $end
$var wire 1 ' K $end
$var wire 1 ( RST $end
$var wire 1 ) clk $end
$var wire 4 * q [3:0] $end
$scope module JK1 $end
$var wire 1 & J $end
$var wire 1 ' K $end
$var wire 1 ( RST $end
$var wire 1 ) clk $end
$var reg 1 + Q $end
$upscope $end
$scope module JK2 $end
$var wire 1 & J $end
$var wire 1 ' K $end
$var wire 1 ( RST $end
$var wire 1 , clk $end
$var reg 1 - Q $end
$upscope $end
$scope module JK3 $end
$var wire 1 & J $end
$var wire 1 ' K $end
$var wire 1 ( RST $end
$var wire 1 . clk $end
$var reg 1 / Q $end
$upscope $end
$scope module JK4 $end
$var wire 1 & J $end
$var wire 1 ' K $end
$var wire 1 ( RST $end
$var wire 1 0 clk $end
$var reg 1 1 Q $end
$upscope $end
$upscope $end
$upscope $end
$enddefinitions $end
#0
$dumpvars
x1
x0
x/
x.
x-
x,
x+
bx *
0)
1(
0'
0&
0%
1$
0#
0"
bx !
$end
#50000
11
10
1/
1.
1-
1,
1+
b1111 !
b1111 *
1%
1)
#100000
0%
0)
#150000
1%
1)
#200000
1#
1'
1"
1&
0$
0(
0%
0)
#250000
0,
0+
b1110 !
b1110 *
1%
1)
#300000
0%
0)
#350000
0.
0-
1,
1+
b1101 !
b1101 *
1%
1)
#400000
0%
0)
#450000
0,
0+
b1100 !
b1100 *
1%
1)
#500000
0%
0)
#550000
00
0/
1.
1-
1,
1+
b1011 !
b1011 *
1%
1)
#600000
0%
0)
#650000
0,
0+
b1010 !
b1010 *
1%
1)
#700000
0%
0)
#750000
0.
0-
1,
1+
b1001 !
b1001 *
1%
1)
#800000
0%
0)
#850000
0,
0+
b1000 !
b1000 *
1%
1)
#900000
0%
0)
#950000
01
10
1/
1.
1-
1,
1+
b111 !
b111 *
1%
1)
#1000000
0%
0)
#1050000
0,
0+
b110 !
b110 *
1%
1)
#1100000
0%
0)
#1150000
0.
0-
1,
1+
b101 !
b101 *
1%
1)
#1200000
0%
0)
#1250000
0,
0+
b100 !
b100 *
1%
1)
#1300000
0%
0)
#1350000
00
0/
1.
1-
1,
1+
b11 !
b11 *
1%
1)
#1400000
0%
0)
#1450000
0,
0+
b10 !
b10 *
1%
1)
#1500000
0%
0)
#1550000
0.
0-
1,
1+
b1 !
b1 *
1%
1)
#1600000
0%
0)
#1650000
0,
0+
b0 !
b0 *
1%
1)
#1700000
0%
0)
#1750000
11
10
1/
1.
1-
1,
1+
b1111 !
b1111 *
1%
1)
#1800000
0%
0)
1$
1(
#1850000
1%
1)
#1900000
0%
0)
#1950000
1%
1)
#2000000
0$
0(
0%
0)
#2050000
0,
0+
b1110 !
b1110 *
1%
1)
#2100000
0%
0)
#2150000
0.
0-
1,
1+
b1101 !
b1101 *
1%
1)
