DAY_17/design.sv
// Code your design here
`timescale 10ns/1ps

module bin2bcd(input [3:0] bin,
                 output reg [4:0] bcd
                );
  
  always@(bin)
    
    begin
      bcd[0] = bin [0];
      bcd[1] = (bin[3] & bin[2] & ~bin[1]) | (~bin[3] & bin[1]);
      bcd[2] = (~bin[3] & bin[2]) | (bin[2] & bin[1]);
      bcd[3] = bin[3] & ~bin[2] & ~bin[1];
      bcd[4] = (bin[3] & bin[2] ) | (bin[3] & bin[1]); 
    end
  
endmodule

DAY_17/testbench.sv
// Code your testbench here
// or browse Examples
`timescale 10ns/1ps


module bin2bcd_tb;
  
  wire [3:0] bcd;
  reg [3:0] bin;

  bin2bcd DUT(.bin(bin),.bcd(bcd));
  
  
  initial 
    begin
      $dumpfile("dump.vcd");
      $dumpvars;
    end
 
  initial 
    begin
           #10      bin=4'b0000;
	       #10      bin=4'b0001;
	       #10      bin=4'b0010;
	       #10      bin=4'b0011;
	       #10      bin=4'b0100;
	       #10      bin=4'b0101;
	       #10      bin=4'b0110;
	       #10      bin=4'b0111;
	       #10      bin=4'b1000;
	       #10      bin=4'b1001;
	       #10      bin=4'b1010;
	       #10      bin=4'b1011;
	       #10      bin=4'b1100;
	       #10      bin=4'b1101;
	       #10   	bin=4'b1110;
	       #10      bin=4'b1111;
    
  end
   
endmodule

DAY_17/dump.vcd
$date
	Fri May 12 04:52:36 2023
$end
$version
	Icarus Verilog
$end
$timescale
	1ps
$end
$scope module bin2bcd_tb $end
$var wire 4 ! bcd [3:0] $end
$var reg 4 " bin [3:0] $end
$scope module DUT $end
$var wire 4 # bin [3:0] $end
$var reg 5 $ bcd [4:0] $end
$upscope $end
$upscope $end
$enddefinitions $end
#0
$dumpvars
bx $
bx #
bx "
bx !
$end
#100000
b0 !
b0 $
b0 "
b0 #
#200000
b1 !
b1 $
b1 "
b1 #
#300000
b10 !
b10 $
b10 "
b10 #
#400000
b11 !
b11 $
b11 "
b11 #
#500000
b100 !
b100 $
b100 "
b100 #
#600000
b101 !
b101 $
b101 "
b101 #
#700000
b110 !
b110 $
b110 "
b110 #
#800000
b111 !
b111 $
b111 "
b111 #
#900000
b1000 !
b1000 $
b1000 "
b1000 #
#1000000
b1001 !
b1001 $
b1001 "
b1001 #
#1100000
b0 !
b10000 $
b1010 "
b1010 #
#1200000
b1 !
b10001 $
b1011 "
b1011 #
#1300000
b10 !
b10010 $
b1100 "
b1100 #
#1400000
b11 !
b10011 $
b1101 "
b1101 #
#1500000
b100 !
b10100 $
b1110 "
b1110 #
#1600000
b101 !
b10101 $
b1111 "
b1111 #
