DAY_18/design.sv
`timescale 1ns/10ps

module clock( input enable,
             output reg clk);
  
parameter FREQ = 100000; //khz
parameter PHASE = 0;
parameter DUTY = 50;
  
  real CLK_PERIOD = 1/(FREQ * 1e3) * 1e9; //to time scale and in ns
  real CLK_ON	  = DUTY/CLK_PERIOD *100;
  real CLK_OFF	  = ((100-DUTY)/CLK_PERIOD) * 100 ;
  
  
  reg clk_enabled;
  
  initial begin
    clk<=0;
    clk_enabled=0;
  end
  
  
  always@(posedge enable)
    begin
      if(enable)
        clk_enabled=1;
      else
        clk_enabled=0;
    end
  
  
  always@(posedge clk_enabled)
  begin
            if(clk_enabled)
	begin
	clk=1;
    	while (clk_enabled)
          		begin
         		   #(CLK_ON) clk = 0;
            		  #(CLK_OFF) clk = 1;
          		end
	clk=0;
    	end 
   end

endmodule

DAY_18/testbench.sv
`timescale 1ns/10ps
module clock_tb;
  
  wire clock_1;
  wire clock_2;
  reg enable;
  reg [7:0] enable_delay;
  
  clock dut1(.enable(enable),
             .clk(clock_1));
  clock #(.FREQ(50000)) dut2(.enable(enable),
                             .clk(clock_2));
  
  initial begin
    enable = 0;
    $dumpfile("dump.vcd");
  	$dumpvars;
  end
  
  initial 
    begin
      enable_delay = $random;
      for(int i = 0; i<20 ;i=i+1)
        begin
          #(enable_delay) enable = ~enable;
        end
    #100 $finish;
    end
  
endmodule

DAY_18/dump.vcd
$date
Sat May 13 10:55:53 2023
$end
$version
Riviera-PRO Version 2022.04.117.8517
$end
$timescale
10 ps
$end

$scope module clock_tb $end
$var wire 1 ! clock_1 $end
$var wire 1 " clock_2 $end
$var reg 1 # enable $end
$var reg 8 $ enable_delay [7:0] $end

$scope module dut1 $end
$var wire 1 % enable $end
$var reg 1 & clk $end
$var real 64 ' CLK_PERIOD $end
$var real 64 ( CLK_ON $end
$var real 64 ) CLK_OFF $end
$var reg 1 * clk_enabled $end
$var parameter 32 + FREQ [31:0] $end
$var parameter 32 , PHASE [31:0] $end
$var parameter 32 - DUTY [31:0] $end
$upscope $end


$scope module dut2 $end
$var wire 1 % enable $end
$var reg 1 . clk $end
$var real 64 / CLK_PERIOD $end
$var real 64 0 CLK_ON $end
$var real 64 1 CLK_OFF $end
$var reg 1 2 clk_enabled $end
$var parameter 32 3 FREQ [31:0] $end
$var parameter 32 4 PHASE [31:0] $end
$var parameter 32 5 DUTY [31:0] $end
$upscope $end

$upscope $end

$enddefinitions $end
$dumpvars
0!
0"
0#
b100100 $
0%
0&
r10 '
r500 (
r500 )
0*
b11000011010100000 +
b0 ,
b110010 -
0.
r20 /
r250 0
r250 1
02
b1100001101010000 3
b0 4
b110010 5
$end
#3600
1#
1%
1*
12
1&
1.
1"
1!
#7200
0#
0%
#10800
1#
1%
#14400
0#
0%
#18000
1#
1%
#21600
0#
0%
#25200
1#
1%
#28600
0.
0"
#28800
0#
0%
#32400
1#
1%
#36000
0#
0%
#39600
1#
1%
#43200
0#
0%
#46800
1#
1%
#50400
0#
0%
#53600
0&
1.
1"
0!
#54000
1#
1%
#57600
0#
0%
#61200
1#
1%
#64800
0#
0%
#68400
1#
1%
#72000
0#
0%
