DAY_14/design.sv
 `timescale 10ns / 1ps
	
//using Behavioural Modelling
module Binary_to_Gray(
	    				input [3:0] b,       
	    				output reg[3:0] g  
  
	    				);
      
always@(b)
	 begin
       g[0]=b[1]^b[0];   
       g[1]=b[2]^b[1];
       g[2]=b[3]^b[2];
       g[3]=b[3];
	 end
endmodule

DAY_14/testbench.sv
`timescale 10ns/1ps
module Binary_to_Gray_tb;
  
  reg [3:0]b;

  wire [3:0]g;

	      
   initial
    begin
      $dumpfile("dump.vcd");
      $dumpvars;
    end
  
  
  Binary_to_Gray DUT(.b(b),
                     .g(g));
  
	initial 
      begin
           #10   b=4'b0000;
	       #10   b=4'b0001;
	       #10   b=4'b0010;
	       #10   b=4'b0011;
	       #10   b=4'b0100;
	       #10   b=4'b0101;
	       #10   b=4'b0110;
	       #10   b=4'b0111;
	       #10   b=4'b1000;
	       #10   b=4'b1001;
	       #10   b=4'b1010;
	       #10   b=4'b1011;
	       #10   b=4'b1100;
	       #10   b=4'b1101;
	       #10   b=4'b1110;
	       #10   b=4'b1111;
	  end
endmodule

DAY_14/dump.vcd
$date
	Sun May  7 04:07:26 2023
$end
$version
	Icarus Verilog
$end
$timescale
	1ps
$end
$scope module Binary_to_Gray_tb $end
$var wire 4 ! g [3:0] $end
$var reg 4 " b [3:0] $end
$scope module DUT $end
$var wire 4 # b [3:0] $end
$var reg 4 $ g [3:0] $end
$upscope $end
$upscope $end
$enddefinitions $end
#0
$dumpvars
bx $
bx #
bx "
bx !
$end
#100000
b0 $
b0 !
b0 "
b0 #
#200000
b1 $
b1 !
b1 "
b1 #
#300000
b11 !
b11 $
b10 "
b10 #
#400000
b10 $
b10 !
b11 "
b11 #
#500000
b110 !
b110 $
b100 "
b100 #
#600000
b111 $
b111 !
b101 "
b101 #
#700000
b101 !
b101 $
b110 "
b110 #
#800000
b100 $
b100 !
b111 "
b111 #
#900000
b1100 !
b1100 $
b1000 "
b1000 #
#1000000
b1101 $
b1101 !
b1001 "
b1001 #
#1100000
b1111 !
b1111 $
b1010 "
b1010 #
#1200000
b1110 $
b1110 !
b1011 "
b1011 #
#1300000
b1010 !
b1010 $
b1100 "
b1100 #
#1400000
b1011 $
b1011 !
b1101 "
b1101 #
#1500000
b1001 !
b1001 $
b1110 "
b1110 #
#1600000
b1000 $
b1000 !
b1111 "
b1111 #
