DAY_11/design.sv
`timescale 10ns/1ps
	
module encoder_8x3 (din, dout); //behavioral model;
	  input [7:0] din;
	  output [2:0] dout;
	  reg [2:0] dout;
		always @(din)
			begin
	          if (din ==8'b00000001) dout=3'b000;
	            else if (din==8'b00000010) dout=3'b001;
	              else if (din==8'b00000100) dout=3'b010;
	                else if (din==8'b00001000) dout=3'b011;
	                  else if (din==8'b00010000) dout=3'b100;
	                    else if (din ==8'b00100000) dout=3'b101;
	                      else if (din==8'b01000000) dout=3'b110;
	                        else if (din==8'b10000000) dout=3'b111;
	          else dout=3'bX;
			end
	endmodule

DAY_11/testbench.sv
`timescale 10ns/1ps

module encoder_tb;
  
  reg [7:0] d;
  wire [2:0] q;
  
  encoder_8x3 DUT (.din(d), .dout(q));
  
  initial 
    begin
      $dumpfile("dump.vcd");
      $dumpvars;
    end
  
  
initial 
  begin
  
    #10 d =8'b10000000;
    #10 d =8'b01000000;
    #10 d =8'b00100000;
    #10 d =8'b00010000;
    #10 d =8'b00001000;
    #10 d =8'b00000100;
    #10 d =8'b00000010;
    #10 d =8'b00000001;
    
    #10 $finish;
end
endmodule

DAY_11/dump.vcd
$date
	Sat May  6 17:21:32 2023
$end
$version
	Icarus Verilog
$end
$timescale
	1ps
$end
$scope module encoder_tb $end
$var wire 3 ! q [2:0] $end
$var reg 8 " d [7:0] $end
$scope module DUT $end
$var wire 8 # din [7:0] $end
$var reg 3 $ dout [2:0] $end
$upscope $end
$upscope $end
$enddefinitions $end
#0
$dumpvars
bx $
bx #
bx "
bx !
$end
#100000
b111 $
b111 !
b10000000 "
b10000000 #
#200000
b110 $
b110 !
b1000000 "
b1000000 #
#300000
b101 $
b101 !
b100000 "
b100000 #
#400000
b100 $
b100 !
b10000 "
b10000 #
#500000
b11 $
b11 !
b1000 "
b1000 #
#600000
b10 $
b10 !
b100 "
b100 #
#700000
b1 $
b1 !
b10 "
b10 #
#800000
b0 $
b0 !
b1 "
b1 #
