DAY_19/design.sv
`timescale 10ns/1ps

module ALU(input [7:0] A,B,
           input [3:0] opcode,
           output reg carry_flag=1'b0,
 		   output reg z_flag=1'b0,
 		   output reg [8:0] out);
 
  always @(opcode,A,B)
    begin
      case(opcode)
        
         4'b0000:
           begin
             out = A + B ;
             carry_flag  = out[8];
             z_flag  = (out == 1'b0);
           end
        
         4'b0001:
           begin
             out = A - B ;

             carry_flag  = out[8];
             z_flag  = (out == 1'b0);
             
           end
        
         4'b0010:
           begin
           	  out = A * B;
              z_flag  = (out == 1'b0);
           end  
         4'b0011: 
           begin
             if(B) begin
               out = A/B;
              z_flag  = (out == 1'b0);
             end
           end
         4'b0100: // Logical shift left
           out = A<<1;
         4'b0101: // Logical shift right
           out = A>>1;
         4'b0110: // Rotate left
           out = {A[6:0],A[7]};
         4'b0111: // Rotate right
           out = {A[0],A[7:1]};
          4'b1000: 
           out = A & B;
          4'b1001: 
           out = A | B;
          4'b1010:
           out = A ^ B;
          4'b1011: 
           out = ~(A | B);
          4'b1100: 
           out = ~(A & B);
          4'b1101: 
           out = ~(A ^ B);
          4'b1110: // Greater than
           out = (A>B)?8'd1:8'd0 ;
          4'b1111: // Equal to
            out = (A==B)?8'd1:8'd0 ;
  	 default:  
       begin
       out = 16'b0;
	   carry_flag  = 1'b0;
	   z_flag = 1'b0; 
       end  
     endcase
    end  
endmodule

DAY_19/testbench.sv
`timescale 10ns/1ps

module alu_tb;
  
  reg [7:0] A,B;
  reg [3:0] opcode;
  wire z_flag;
  wire carry_flag;
  wire [15:0] out;
  integer i;
  
  ALU alu(.A(A),.B(B),.out(out),.carry_flag(carry_flag),.z_flag(z_flag),.opcode(opcode));
  
  
  initial
    begin
      $dumpfile("dump.vcd");
      $dumpvars;
    end
  
  initial
    begin
      opcode = 4'b0;
      A	    = 8'b0;
      B     = 8'b0;
      
      #100;
      
      A = 8'h69;
      B = 8'h35;
      
      for(i = 0 ; i < 16 ; i=i+1'b1)
        begin
          opcode = i ;
          #50;
        end
    end
endmodule

DAY_19/dump.vcd
$date
Sun May 14 00:32:51 2023
$end
$version
Riviera-PRO Version 2022.04.117.8517
$end
$timescale
1 ps
$end

$scope module alu_tb $end
$var wire 1 ! z_flag $end
$var wire 1 " carry_flag $end
$var wire 16 # out [15:0] $end
$var reg 8 $ A [7:0] $end
$var reg 8 % B [7:0] $end
$var reg 4 & opcode [3:0] $end
$var integer 32 ' i $end

$scope module alu $end
$var wire 8 ( A [7:0] $end
$var wire 8 ) B [7:0] $end
$var wire 4 * opcode [3:0] $end
$var reg 1 + carry_flag $end
$var reg 1 , z_flag $end
$var reg 9 - out [8:0] $end
$upscope $end

$upscope $end

$enddefinitions $end
$dumpvars
1!
0"
bz000000000 #
b0 $
b0 %
b0 &
bx '
b0 (
b0 )
b0 *
0+
1,
b0 -
$end
#1000000
b1101001 $
b110101 %
b0 '
b110101 )
b1101001 (
b10011110 -
0,
0!
bz010011110 #
#1500000
b1 '
b1 &
b1 *
b110100 -
bz000110100 #
#2000000
b10 '
b10 &
b10 *
b110111101 -
bz110111101 #
#2500000
b11 '
b11 &
b11 *
b1 -
bz000000001 #
#3000000
b100 '
b100 &
b100 *
b11010010 -
bz011010010 #
#3500000
b101 '
b101 &
b101 *
b110100 -
bz000110100 #
#4000000
b110 '
b110 &
b110 *
b11010010 -
bz011010010 #
#4500000
b111 '
b111 &
b111 *
b10110100 -
bz010110100 #
#5000000
b1000 '
b1000 &
b1000 *
b100001 -
bz000100001 #
#5500000
b1001 '
b1001 &
b1001 *
b1111101 -
bz001111101 #
#6000000
b1010 '
b1010 &
b1010 *
b1011100 -
bz001011100 #
#6500000
b1011 '
b1011 &
b1011 *
b110000010 -
bz110000010 #
#7000000
b1100 '
b1100 &
b1100 *
b111011110 -
bz111011110 #
#7500000
b1101 '
b1101 &
b1101 *
b110100011 -
bz110100011 #
#8000000
b1110 '
b1110 &
b1110 *
b1 -
bz000000001 #
#8500000
b1111 '
b1111 &
b1111 *
b0 -
bz000000000 #
#9000000
b10000 '
