DAY_36/design.sv
`timescale 10ns/1ns

module PISO(input clk,clr,load,
            input [7:0] data_in,
            output reg data_out
           );
  
  
  reg [7:0] data_reg;
  
  
  always@(posedge clk or negedge clr)
    begin
      if(~clr)
        data_reg <= 0;
      
      else
        begin 
          if(load)
          {data_reg,data_out} <= {data_in,1'b0}; //clear the ouput and load the data into temp register
          else 
          {data_reg,data_out} <= {1'b0,data_reg[7:0]};
        end
    end
  
endmodule

DAY_36/testbench.sv
`timescale 10ns/10ns

module PISO_TB;
  
  reg clk,clr,load;
  reg [7:0] data_in;
  
  wire data_out;
  
  
  PISO DUT(clk,clr,load,data_in,data_out);
  
   always #1 clk = ~clk;
  
  initial
    begin
    $dumpfile("dump.vcd");
    $dumpvars;
    end
  
  initial 
    begin
      clk=0;
      clr=0;
      load=0;
      data_in=8'b00000000;
      
      
      #5 clr = 1;

      #10 load = 1; 
      
      
      data_in = 8'd15;
      #5 load = 0;

      #10 load = 1; 
      
      data_in = 8'd255;
      #5 load = 0;

      #10 load = 1; 
      
      data_in = 8'd128;
      #5 load = 0;

      #100 $finish;
    end
  
endmodule

DAY_36/dump.vcd
$date
	Tue Jun 20 05:01:59 2023
$end
$version
	Icarus Verilog
$end
$timescale
	1ns
$end
$scope module PISO_TB $end
$var wire 1 ! data_out $end
$var reg 1 " clk $end
$var reg 1 # clr $end
$var reg 8 $ data_in [7:0] $end
$var reg 1 % load $end
$scope module DUT $end
$var wire 1 & clk $end
$var wire 1 ' clr $end
$var wire 8 ( data_in [7:0] $end
$var wire 1 ) load $end
$var reg 1 * data_out $end
$var reg 8 + data_reg [7:0] $end
$upscope $end
$upscope $end
$enddefinitions $end
#0
$dumpvars
b0 +
x*
0)
b0 (
0'
0&
0%
b0 $
0#
0"
x!
$end
#10
1"
1&
#20
0"
0&
#30
1"
1&
#40
0"
0&
#50
0*
0!
1"
1&
1#
1'
#60
0"
0&
#70
1"
1&
#80
0"
0&
#90
1"
1&
#100
0"
0&
#110
1"
1&
#120
0"
0&
#130
1"
1&
#140
0"
0&
#150
b1111 +
1"
1&
b1111 $
b1111 (
1%
1)
#160
0"
0&
#170
1"
1&
#180
0"
0&
#190
1"
1&
#200
0"
0&
0%
0)
#210
b111 +
1*
1!
1"
1&
#220
0"
0&
#230
b11 +
1"
1&
#240
0"
0&
#250
b1 +
1"
1&
#260
0"
0&
#270
b0 +
1"
1&
#280
0"
0&
#290
0*
0!
1"
1&
#300
0"
0&
b11111111 $
b11111111 (
1%
1)
#310
b11111111 +
1"
1&
#320
0"
0&
#330
1"
1&
#340
0"
0&
#350
b1111111 +
1*
1!
1"
1&
0%
0)
#360
0"
0&
#370
b111111 +
1"
1&
#380
0"
0&
#390
b11111 +
1"
1&
#400
0"
0&
#410
b1111 +
1"
1&
#420
0"
0&
#430
b111 +
1"
1&
#440
0"
0&
#450
b10000000 +
0*
0!
1"
1&
b10000000 $
b10000000 (
1%
1)
#460
0"
0&
#470
1"
1&
#480
0"
0&
#490
1"
1&
#500
0"
0&
0%
0)
#510
b1000000 +
1"
1&
#520
0"
0&
#530
b100000 +
1"
1&
#540
0"
0&
#550
b10000 +
1"
1&
#560
0"
0&
#570
b1000 +
1"
1&
#580
0"
0&
#590
b100 +
1"
1&
#600
0"
0&
#610
b10 +
1"
1&
#620
0"
0&
#630
b1 +
1"
1&
#640
0"
0&
#650
b0 +
1*
1!
1"
1&
#660
0"
0&
#670
0*
0!
1"
1&
