DAY_34/design.sv
`timescale 100ns/100ns

module clock_divider #(parameter N=500) (
  											input clk, rst,
    										output reg clk_out
    										);
	
localparam FIXED_OUT = ((N/2)- 1);
  
  
reg [31:0] count;
  
wire COMPARATOR_OUT;

assign COMPARATOR_OUT = (count == FIXED_OUT);	

always @ (posedge clk , posedge rst) //synchronous reset
		begin
    	if (rst) 
          count <= 0;
        else if (COMPARATOR_OUT) 
          count <= 0;		// Resets the counter when FIXED OUT is reached
        else 
          count <= count + 1; 
		end

  always @ (posedge clk, posedge rst)
begin
    if (rst) 
      clk_out <= 0;
    else if (COMPARATOR_OUT) 
      clk_out <= !clk_out;	
// T-FF with COMPARATOR_OUT as input signal or can be inferred as an DFF with COMPARATOR_OUT  as the control signal for the ENABLE.
    else
        clk_out <= clk_out; //to avoid inferred latch
end
endmodule

DAY_34/testbench.sv
`timescale 100ns/100ns

module clock_divider_tb;
  
  reg clk,rst;
  wire clk_out;
  
  clock_divider #(.N(500)) DUT1 (.clk(clk),.rst(rst),.clk_out(clk_out));
  //clock_divider #(.N(100)) DUT2 (.clk(clk),.rst(rst),.clk_out(clk_out));
  always #5 clk = ~ clk; //10MHZ signal
  
  initial 
    begin
      clk = 0;
      rst = 1;
      #5 rst = 0;
      #10000 $finish;
    end
  
  
  initial 
    begin
  $dumpfile("dump.vcd");
      $dumpvars;
    end 
endmodule

DAY_34/dump.vcd
$date
Fri Jun 16 10:54:20 2023
$end
$version
Riviera-PRO Version 2022.04.117.8517
$end
$timescale
100 ns
$end

$scope module clock_divider_tb $end
$var wire 1 ! clk_out $end
$var reg 1 " clk $end
$var reg 1 # rst $end

$scope module DUT1 $end
$var wire 1 $ clk $end
$var wire 1 % rst $end
$var wire 1 & COMPARATOR_OUT $end
$var reg 1 ' clk_out $end
$var reg 32 ( count [31:0] $end
$var parameter 32 ) N [31:0] $end
$var parameter 32 * FIXED_OUT [31:0] $end
$upscope $end

$upscope $end

$enddefinitions $end
$dumpvars
0!
0"
1#
0$
1%
0&
0'
b0 (
b111110100 )
b11111001 *
$end
#5
1"
0#
0%
1$
b1 (
#10
0"
0$
#15
1"
1$
b10 (
#20
0"
0$
#25
1"
1$
b11 (
#30
0"
0$
#35
1"
1$
b100 (
#40
0"
0$
#45
1"
1$
b101 (
#50
0"
0$
#55
1"
1$
b110 (
#60
0"
0$
#65
1"
1$
b111 (
#70
0"
0$
#75
1"
1$
b1000 (
#80
0"
0$
#85
1"
1$
b1001 (
#90
0"
0$
#95
1"
1$
b1010 (
#100
0"
0$
#105
1"
1$
b1011 (
#110
0"
0$
#115
1"
1$
b1100 (
#120
0"
0$
#125
1"
1$
b1101 (
#130
0"
0$
#135
1"
1$
b1110 (
#140
0"
0$
#145
1"
1$
b1111 (
#150
0"
0$
#155
1"
1$
b10000 (
#160
0"
0$
#165
1"
1$
b10001 (
#170
0"
0$
#175
1"
1$
b10010 (
#180
0"
0$
#185
1"
1$
b10011 (
#190
0"
0$
#195
1"
1$
b10100 (
#200
0"
0$
#205
1"
1$
b10101 (
#210
0"
0$
#215
1"
1$
b10110 (
#220
0"
0$
#225
1"
1$
b10111 (
#230
0"
0$
#235
1"
1$
b11000 (
#240
0"
0$
#245
1"
1$
b11001 (
#250
0"
0$
#255
1"
1$
b11010 (
#260
0"
0$
#265
1"
1$
b11011 (
#270
0"
0$
#275
1"
1$
b11100 (
#280
0"
0$
#285
1"
1$
b11101 (
#290
0"
0$
#295
1"
1$
b11110 (
#300
0"
0$
#305
1"
1$
b11111 (
#310
0"
0$
#315
1"
1$
b100000 (
#320
0"
0$
#325
1"
1$
b100001 (
#330
0"
0$
#335
1"
1$
b100010 (
#340
0"
0$
#345
1"
1$
b100011 (
#350
0"
0$
#355
1"
1$
b100100 (
#360
0"
0$
#365
1"
1$
b100101 (
#370
0"
0$
#375
1"
1$
b100110 (
#380
0"
0$
#385
1"
1$
b100111 (
#390
0"
0$
#395
1"
1$
b101000 (
#400
0"
0$
#405
1"
1$
b101001 (
#410
0"
0$
#415
1"
1$
b101010 (
#420
0"
0$
#425
1"
1$
b101011 (
#430
0"
0$
#435
1"
1$
b101100 (
#440
0"
0$
#445
1"
1$
b101101 (
#450
0"
0$
#455
1"
1$
b101110 (
#460
0"
0$
#465
1"
1$
b101111 (
#470
0"
0$
#475
1"
1$
b110000 (
#480
0"
0$
#485
1"
1$
b110001 (
#490
0"
0$
#495
1"
1$
b110010 (
#500
0"
0$
#505
1"
1$
b110011 (
#510
0"
0$
#515
1"
1$
b110100 (
#520
0"
0$
#525
1"
1$
b110101 (
#530
0"
0$
#535
1"
1$
b110110 (
#540
0"
0$
#545
1"
1$
b110111 (
#550
0"
0$
#555
1"
1$
b111000 (
#560
0"
0$
#565
1"
1$
b111001 (
#570
0"
0$
#575
1"
1$
b111010 (
#580
0"
0$
#585
1"
1$
b111011 (
#590
0"
0$
#595
1"
1$
b111100 (
#600
0"
0$
#605
1"
1$
b111101 (
#610
0"
0$
#615
1"
1$
b111110 (
#620
0"
0$
#625
1"
1$
b111111 (
#630
0"
0$
#635
1"
1$
b1000000 (
#640
0"
0$
#645
1"
1$
b1000001 (
#650
0"
0$
#655
1"
1$
b1000010 (
#660
0"
0$
#665
1"
1$
b1000011 (
#670
0"
0$
#675
1"
1$
b1000100 (
#680
0"
0$
#685
1"
1$
b1000101 (
#690
0"
0$
#695
1"
1$
b1000110 (
#700
0"
0$
#705
1"
1$
b1000111 (
#710
0"
0$
#715
1"
1$
b1001000 (
#720
0"
0$
#725
1"
1$
b1001001 (
#730
0"
0$
#735
1"
1$
b1001010 (
#740
0"
0$
#745
1"
1$
b1001011 (
#750
0"
0$
#755
1"
1$
b1001100 (
#760
0"
0$
#765
1"
1$
b1001101 (
#770
0"
0$
#775
1"
1$
b1001110 (
#780
0"
0$
#785
1"
1$
b1001111 (
#790
0"
0$
#795
1"
1$
b1010000 (
#800
0"
0$
#805
1"
1$
b1010001 (
#810
0"
0$
#815
1"
1$
b1010010 (
#820
0"
0$
#825
1"
1$
b1010011 (
#830
0"
0$
#835
1"
1$
b1010100 (
#840
0"
0$
#845
1"
1$
b1010101 (
#850
0"
0$
#855
1"
1$
b1010110 (
#860
0"
0$
#865
1"
1$
b1010111 (
#870
0"
0$
#875
1"
1$
b1011000 (
#880
0"
0$
#885
1"
1$
b1011001 (
#890
0"
0$
#895
1"
1$
b1011010 (
#900
0"
0$
#905
1"
1$
b1011011 (
#910
0"
0$
#915
1"
1$
b1011100 (
#920
0"
0$
#925
1"
1$
b1011101 (
#930
0"
0$
#935
1"
1$
b1011110 (
#940
0"
0$
#945
1"
1$
b1011111 (
#950
0"
0$
#955
1"
1$
b1100000 (
#960
0"
0$
#965
1"
1$
b1100001 (
#970
0"
0$
#975
1"
1$
b1100010 (
#980
0"
0$
#985
1"
1$
b1100011 (
#990
0"
0$
#995
1"
1$
b1100100 (
#1000
0"
0$
#1005
1"
1$
b1100101 (
#1010
0"
0$
#1015
1"
1$
b1100110 (
#1020
0"
0$
#1025
1"
1$
b1100111 (
#1030
0"
0$
#1035
1"
1$
b1101000 (
#1040
0"
0$
#1045
1"
1$
b1101001 (
#1050
0"
0$
#1055
1"
1$
b1101010 (
#1060
0"
0$
#1065
1"
1$
b1101011 (
#1070
0"
0$
#1075
1"
1$
b1101100 (
#1080
0"
0$
#1085
1"
1$
b1101101 (
#1090
0"
0$
#1095
1"
1$
b1101110 (
#1100
0"
0$
#1105
1"
1$
b1101111 (
#1110
0"
0$
#1115
1"
1$
b1110000 (
#1120
0"
0$
#1125
1"
1$
b1110001 (
#1130
0"
0$
#1135
1"
1$
b1110010 (
#1140
0"
0$
#1145
1"
1$
b1110011 (
#1150
0"
0$
#1155
1"
1$
b1110100 (
#1160
0"
0$
#1165
1"
1$
b1110101 (
#1170
0"
0$
#1175
1"
1$
b1110110 (
#1180
0"
0$
#1185
1"
1$
b1110111 (
#1190
0"
0$
#1195
1"
1$
b1111000 (
#1200
0"
0$
#1205
1"
1$
b1111001 (
#1210
0"
0$
#1215
1"
1$
b1111010 (
#1220
0"
0$
#1225
1"
1$
b1111011 (
#1230
0"
0$
#1235
1"
1$
b1111100 (
#1240
0"
0$
#1245
1"
1$
b1111101 (
#1250
0"
0$
#1255
1"
1$
b1111110 (
#1260
0"
0$
#1265
1"
1$
b1111111 (
#1270
0"
0$
#1275
1"
1$
b10000000 (
#1280
0"
0$
#1285
1"
1$
b10000001 (
#1290
0"
0$
#1295
1"
1$
b10000010 (
#1300
0"
0$
#1305
1"
1$
b10000011 (
#1310
0"
0$
#1315
1"
1$
b10000100 (
#1320
0"
0$
#1325
1"
1$
b10000101 (
#1330
0"
0$
#1335
1"
1$
b10000110 (
#1340
0"
0$
#1345
1"
1$
b10000111 (
#1350
0"
0$
#1355
1"
1$
b10001000 (
#1360
0"
0$
#1365
1"
1$
b10001001 (
#1370
0"
0$
#1375
1"
1$
b10001010 (
#1380
0"
0$
#1385
1"
1$
b10001011 (
#1390
0"
0$
#1395
1"
1$
b10001100 (
#1400
0"
0$
#1405
1"
1$
b10001101 (
#1410
0"
0$
#1415
1"
1$
b10001110 (
#1420
0"
0$
#1425
1"
1$
b10001111 (
#1430
0"
0$
#1435
1"
1$
b10010000 (
#1440
0"
0$
#1445
1"
1$
b10010001 (
#1450
0"
0$
#1455
1"
1$
b10010010 (
#1460
0"
0$
#1465
1"
1$
b10010011 (
#1470
0"
0$
#1475
1"
1$
b10010100 (
#1480
0"
0$
#1485
1"
1$
b10010101 (
#1490
0"
0$
#1495
1"
1$
b10010110 (
#1500
0"
0$
#1505
1"
1$
b10010111 (
#1510
0"
0$
#1515
1"
1$
b10011000 (
#1520
0"
0$
#1525
1"
1$
b10011001 (
#1530
0"
0$
#1535
1"
1$
b10011010 (
#1540
0"
0$
#1545
1"
1$
b10011011 (
#1550
0"
0$
#1555
1"
1$
b10011100 (
#1560
0"
0$
#1565
1"
1$
b10011101 (
#1570
0"
0$
#1575
1"
1$
b10011110 (
#1580
0"
0$
#1585
1"
1$
b10011111 (
#1590
0"
0$
#1595
1"
1$
b10100000 (
#1600
0"
0$
#1605
1"
1$
b10100001 (
#1610
0"
0$
#1615
1"
1$
b10100010 (
#1620
0"
0$
#1625
1"
1$
b10100011 (
#1630
0"
0$
#1635
1"
1$
b10100100 (
#1640
0"
0$
#1645
1"
1$
b10100101 (
#1650
0"
0$
#1655
1"
1$
b10100110 (
#1660
0"
0$
#1665
1"
1$
b10100111 (
#1670
0"
0$
#1675
1"
1$
b10101000 (
#1680
0"
0$
#1685
1"
1$
b10101001 (
#1690
0"
0$
#1695
1"
1$
b10101010 (
#1700
0"
0$
#1705
1"
1$
b10101011 (
#1710
0"
0$
#1715
1"
1$
b10101100 (
#1720
0"
0$
#1725
1"
1$
b10101101 (
#1730
0"
0$
#1735
1"
1$
b10101110 (
#1740
0"
0$
#1745
1"
1$
b10101111 (
#1750
0"
0$
#1755
1"
1$
b10110000 (
#1760
0"
0$
#1765
1"
1$
b10110001 (
#1770
0"
0$
#1775
1"
1$
b10110010 (
#1780
0"
0$
#1785
1"
1$
b10110011 (
#1790
0"
0$
#1795
1"
1$
b10110100 (
#1800
0"
0$
#1805
1"
1$
b10110101 (
#1810
0"
0$
#1815
1"
1$
b10110110 (
#1820
0"
0$
#1825
1"
1$
b10110111 (
#1830
0"
0$
#1835
1"
1$
b10111000 (
#1840
0"
0$
#1845
1"
1$
b10111001 (
#1850
0"
0$
#1855
1"
1$
b10111010 (
#1860
0"
0$
#1865
1"
1$
b10111011 (
#1870
0"
0$
#1875
1"
1$
b10111100 (
#1880
0"
0$
#1885
1"
1$
b10111101 (
#1890
0"
0$
#1895
1"
1$
b10111110 (
#1900
0"
0$
#1905
1"
1$
b10111111 (
#1910
0"
0$
#1915
1"
1$
b11000000 (
#1920
0"
0$
#1925
1"
1$
b11000001 (
#1930
0"
0$
#1935
1"
1$
b11000010 (
#1940
0"
0$
#1945
1"
1$
b11000011 (
#1950
0"
0$
#1955
1"
1$
b11000100 (
#1960
0"
0$
#1965
1"
1$
b11000101 (
#1970
0"
0$
#1975
1"
1$
b11000110 (
#1980
0"
0$
#1985
1"
1$
b11000111 (
#1990
0"
0$
#1995
1"
1$
b11001000 (
#2000
0"
0$
#2005
1"
1$
b11001001 (
#2010
0"
0$
#2015
1"
1$
b11001010 (
#2020
0"
0$
#2025
1"
1$
b11001011 (
#2030
0"
0$
#2035
1"
1$
b11001100 (
#2040
0"
0$
#2045
1"
1$
b11001101 (
#2050
0"
0$
#2055
1"
1$
b11001110 (
#2060
0"
0$
#2065
1"
1$
b11001111 (
#2070
0"
0$
#2075
1"
1$
b11010000 (
#2080
0"
0$
#2085
1"
1$
b11010001 (
#2090
0"
0$
#2095
1"
1$
b11010010 (
#2100
0"
0$
#2105
1"
1$
b11010011 (
#2110
0"
0$
#2115
1"
1$
b11010100 (
#2120
0"
0$
#2125
1"
1$
b11010101 (
#2130
0"
0$
#2135
1"
1$
b11010110 (
#2140
0"
0$
#2145
1"
1$
b11010111 (
#2150
0"
0$
#2155
1"
1$
b11011000 (
#2160
0"
0$
#2165
1"
1$
b11011001 (
#2170
0"
0$
#2175
1"
1$
b11011010 (
#2180
0"
0$
#2185
1"
1$
b11011011 (
#2190
0"
0$
#2195
1"
1$
b11011100 (
#2200
0"
0$
#2205
1"
1$
b11011101 (
#2210
0"
0$
#2215
1"
1$
b11011110 (
#2220
0"
0$
#2225
1"
1$
b11011111 (
#2230
0"
0$
#2235
1"
1$
b11100000 (
#2240
0"
0$
#2245
1"
1$
b11100001 (
#2250
0"
0$
#2255
1"
1$
b11100010 (
#2260
0"
0$
#2265
1"
1$
b11100011 (
#2270
0"
0$
#2275
1"
1$
b11100100 (
#2280
0"
0$
#2285
1"
1$
b11100101 (
#2290
0"
0$
#2295
1"
1$
b11100110 (
#2300
0"
0$
#2305
1"
1$
b11100111 (
#2310
0"
0$
#2315
1"
1$
b11101000 (
#2320
0"
0$
#2325
1"
1$
b11101001 (
#2330
0"
0$
#2335
1"
1$
b11101010 (
#2340
0"
0$
#2345
1"
1$
b11101011 (
#2350
0"
0$
#2355
1"
1$
b11101100 (
#2360
0"
0$
#2365
1"
1$
b11101101 (
#2370
0"
0$
#2375
1"
1$
b11101110 (
#2380
0"
0$
#2385
1"
1$
b11101111 (
#2390
0"
0$
#2395
1"
1$
b11110000 (
#2400
0"
0$
#2405
1"
1$
b11110001 (
#2410
0"
0$
#2415
1"
1$
b11110010 (
#2420
0"
0$
#2425
1"
1$
b11110011 (
#2430
0"
0$
#2435
1"
1$
b11110100 (
#2440
0"
0$
#2445
1"
1$
b11110101 (
#2450
0"
0$
#2455
1"
1$
b11110110 (
#2460
0"
0$
#2465
1"
1$
b11110111 (
#2470
0"
0$
#2475
1"
1$
b11111000 (
#2480
0"
0$
#2485
1"
1$
b11111001 (
1&
#2490
0"
0$
#2495
1"
1$
b0 (
1'
0&
1!
#2500
0"
0$
#2505
1"
1$
b1 (
#2510
0"
0$
#2515
1"
1$
b10 (
#2520
0"
0$
#2525
1"
1$
b11 (
#2530
0"
0$
#2535
1"
1$
b100 (
#2540
0"
0$
#2545
1"
1$
b101 (
#2550
0"
0$
#2555
1"
1$
b110 (
#2560
0"
0$
#2565
1"
1$
b111 (
#2570
0"
0$
#2575
1"
1$
b1000 (
#2580
0"
0$
#2585
1"
1$
b1001 (
#2590
0"
0$
#2595
1"
1$
b1010 (
#2600
0"
0$
#2605
1"
1$
b1011 (
#2610
0"
0$
#2615
1"
1$
b1100 (
#2620
0"
0$
#2625
1"
1$
b1101 (
#2630
0"
0$
#2635
1"
1$
b1110 (
#2640
0"
0$
#2645
1"
1$
b1111 (
#2650
0"
0$
#2655
1"
1$
b10000 (
#2660
0"
0$
#2665
1"
1$
b10001 (
#2670
0"
0$
#2675
1"
1$
b10010 (
#2680
0"
0$
#2685
1"
1$
b10011 (
#2690
0"
0$
#2695
1"
1$
b10100 (
#2700
0"
0$
#2705
1"
1$
b10101 (
#2710
0"
0$
#2715
1"
1$
b10110 (
#2720
0"
0$
#2725
1"
1$
b10111 (
#2730
0"
0$
#2735
1"
1$
b11000 (
#2740
0"
0$
#2745
1"
1$
b11001 (
#2750
0"
0$
#2755
1"
1$
b11010 (
#2760
0"
0$
#2765
1"
1$
b11011 (
#2770
0"
0$
#2775
1"
1$
b11100 (
#2780
0"
0$
#2785
1"
1$
b11101 (
#2790
0"
0$
#2795
1"
1$
b11110 (
#2800
0"
0$
#2805
1"
1$
b11111 (
#2810
0"
0$
#2815
1"
1$
b100000 (
#2820
0"
0$
#2825
1"
1$
b100001 (
#2830
0"
0$
#2835
1"
1$
b100010 (
#2840
0"
0$
#2845
1"
1$
b100011 (
#2850
0"
0$
#2855
1"
1$
b100100 (
#2860
0"
0$
#2865
1"
1$
b100101 (
#2870
0"
0$
#2875
1"
1$
b100110 (
#2880
0"
0$
#2885
1"
1$
b100111 (
#2890
0"
0$
#2895
1"
1$
b101000 (
#2900
0"
0$
#2905
1"
1$
b101001 (
#2910
0"
0$
#2915
1"
1$
b101010 (
#2920
0"
0$
#2925
1"
1$
b101011 (
#2930
0"
0$
#2935
1"
1$
b101100 (
#2940
0"
0$
#2945
1"
1$
b101101 (
#2950
0"
0$
#2955
1"
1$
b101110 (
#2960
0"
0$
#2965
1"
1$
b101111 (
#2970
0"
0$
#2975
1"
1$
b110000 (
#2980
0"
0$
#2985
1"
1$
b110001 (
#2990
0"
0$
#2995
1"
1$
b110010 (
#3000
0"
0$
#3005
1"
1$
b110011 (
#3010
0"
0$
#3015
1"
1$
b110100 (
#3020
0"
0$
#3025
1"
1$
b110101 (
#3030
0"
0$
#3035
1"
1$
b110110 (
#3040
0"
0$
#3045
1"
1$
b110111 (
#3050
0"
0$
#3055
1"
1$
b111000 (
#3060
0"
0$
#3065
1"
1$
b111001 (
#3070
0"
0$
#3075
1"
1$
b111010 (
#3080
0"
0$
#3085
1"
1$
b111011 (
#3090
0"
0$
#3095
1"
1$
b111100 (
#3100
0"
0$
#3105
1"
1$
b111101 (
#3110
0"
0$
#3115
1"
1$
b111110 (
#3120
0"
0$
#3125
1"
1$
b111111 (
#3130
0"
0$
#3135
1"
1$
b1000000 (
#3140
0"
0$
#3145
1"
1$
b1000001 (
#3150
0"
0$
#3155
1"
1$
b1000010 (
#3160
0"
0$
#3165
1"
1$
b1000011 (
#3170
0"
0$
#3175
1"
1$
b1000100 (
#3180
0"
0$
#3185
1"
1$
b1000101 (
#3190
0"
0$
#3195
1"
1$
b1000110 (
#3200
0"
0$
#3205
1"
1$
b1000111 (
#3210
0"
0$
#3215
1"
1$
b1001000 (
#3220
0"
0$
#3225
1"
1$
b1001001 (
#3230
0"
0$
#3235
1"
1$
b1001010 (
#3240
0"
0$
#3245
1"
1$
b1001011 (
#3250
0"
0$
#3255
1"
1$
b1001100 (
#3260
0"
0$
#3265
1"
1$
b1001101 (
#3270
0"
0$
#3275
1"
1$
b1001110 (
#3280
0"
0$
#3285
1"
1$
b1001111 (
#3290
0"
0$
#3295
1"
1$
b1010000 (
#3300
0"
0$
#3305
1"
1$
b1010001 (
#3310
0"
0$
#3315
1"
1$
b1010010 (
#3320
0"
0$
#3325
1"
1$
b1010011 (
#3330
0"
0$
#3335
1"
1$
b1010100 (
#3340
0"
0$
#3345
1"
1$
b1010101 (
#3350
0"
0$
#3355
1"
1$
b1010110 (
#3360
0"
0$
#3365
1"
1$
b1010111 (
#3370
0"
0$
#3375
1"
1$
b1011000 (
#3380
0"
0$
#3385
1"
1$
b1011001 (
#3390
0"
0$
#3395
1"
1$
b1011010 (
#3400
0"
0$
#3405
1"
1$
b1011011 (
#3410
0"
0$
#3415
1"
1$
b1011100 (
#3420
0"
0$
#3425
1"
1$
b1011101 (
#3430
0"
0$
#3435
1"
1$
b1011110 (
#3440
0"
0$
#3445
1"
1$
b1011111 (
#3450
0"
0$
#3455
1"
1$
b1100000 (
#3460
0"
0$
#3465
1"
1$
b1100001 (
#3470
0"
0$
#3475
1"
1$
b1100010 (
#3480
0"
0$
#3485
1"
1$
b1100011 (
#3490
0"
0$
#3495
1"
1$
b1100100 (
#3500
0"
0$
#3505
1"
1$
b1100101 (
#3510
0"
0$
#3515
1"
1$
b1100110 (
#3520
0"
0$
#3525
1"
1$
b1100111 (
#3530
0"
0$
#3535
1"
1$
b1101000 (
#3540
0"
0$
#3545
1"
1$
b1101001 (
#3550
0"
0$
#3555
1"
1$
b1101010 (
#3560
0"
0$
#3565
1"
1$
b1101011 (
#3570
0"
0$
#3575
1"
1$
b1101100 (
#3580
0"
0$
#3585
1"
1$
b1101101 (
#3590
0"
0$
#3595
1"
1$
b1101110 (
#3600
0"
0$
#3605
1"
1$
b1101111 (
#3610
0"
0$
#3615
1"
1$
b1110000 (
#3620
0"
0$
#3625
1"
1$
b1110001 (
#3630
0"
0$
#3635
1"
1$
b1110010 (
#3640
0"
0$
#3645
1"
1$
b1110011 (
#3650
0"
0$
#3655
1"
1$
b1110100 (
#3660
0"
0$
#3665
1"
1$
b1110101 (
#3670
0"
0$
#3675
1"
1$
b1110110 (
#3680
0"
0$
#3685
1"
1$
b1110111 (
#3690
0"
0$
#3695
1"
1$
b1111000 (
#3700
0"
0$
#3705
1"
1$
b1111001 (
#3710
0"
0$
#3715
1"
1$
b1111010 (
#3720
0"
0$
#3725
1"
1$
b1111011 (
#3730
0"
0$
#3735
1"
1$
b1111100 (
#3740
0"
0$
#3745
1"
1$
b1111101 (
#3750
0"
0$
#3755
1"
1$
b1111110 (
#3760
0"
0$
#3765
1"
1$
b1111111 (
#3770
0"
0$
#3775
1"
1$
b10000000 (
#3780
0"
0$
#3785
1"
1$
b10000001 (
#3790
0"
0$
#3795
1"
1$
b10000010 (
#3800
0"
0$
#3805
1"
1$
b10000011 (
#3810
0"
0$
#3815
1"
1$
b10000100 (
#3820
0"
0$
#3825
1"
1$
b10000101 (
#3830
0"
0$
#3835
1"
1$
b10000110 (
#3840
0"
0$
#3845
1"
1$
b10000111 (
#3850
0"
0$
#3855
1"
1$
b10001000 (
#3860
0"
0$
#3865
1"
1$
b10001001 (
#3870
0"
0$
#3875
1"
1$
b10001010 (
#3880
0"
0$
#3885
1"
1$
b10001011 (
#3890
0"
0$
#3895
1"
1$
b10001100 (
#3900
0"
0$
#3905
1"
1$
b10001101 (
#3910
0"
0$
#3915
1"
1$
b10001110 (
#3920
0"
0$
#3925
1"
1$
b10001111 (
#3930
0"
0$
#3935
1"
1$
b10010000 (
#3940
0"
0$
#3945
1"
1$
b10010001 (
#3950
0"
0$
#3955
1"
1$
b10010010 (
#3960
0"
0$
#3965
1"
1$
b10010011 (
#3970
0"
0$
#3975
1"
1$
b10010100 (
#3980
0"
0$
#3985
1"
1$
b10010101 (
#3990
0"
0$
#3995
1"
1$
b10010110 (
#4000
0"
0$
#4005
1"
1$
b10010111 (
#4010
0"
0$
#4015
1"
1$
b10011000 (
#4020
0"
0$
#4025
1"
1$
b10011001 (
#4030
0"
0$
#4035
1"
1$
b10011010 (
#4040
0"
0$
#4045
1"
1$
b10011011 (
#4050
0"
0$
#4055
1"
1$
b10011100 (
#4060
0"
0$
#4065
1"
1$
b10011101 (
#4070
0"
0$
#4075
1"
1$
b10011110 (
#4080
0"
0$
#4085
1"
1$
b10011111 (
#4090
0"
0$
#4095
1"
1$
b10100000 (
#4100
0"
0$
#4105
1"
1$
b10100001 (
#4110
0"
0$
#4115
1"
1$
b10100010 (
#4120
0"
0$
#4125
1"
1$
b10100011 (
#4130
0"
0$
#4135
1"
1$
b10100100 (
#4140
0"
0$
#4145
1"
1$
b10100101 (
#4150
0"
0$
#4155
1"
1$
b10100110 (
#4160
0"
0$
#4165
1"
1$
b10100111 (
#4170
0"
0$
#4175
1"
1$
b10101000 (
#4180
0"
0$
#4185
1"
1$
b10101001 (
#4190
0"
0$
#4195
1"
1$
b10101010 (
#4200
0"
0$
#4205
1"
1$
b10101011 (
#4210
0"
0$
#4215
1"
1$
b10101100 (
#4220
0"
0$
#4225
1"
1$
b10101101 (
#4230
0"
0$
#4235
1"
1$
b10101110 (
#4240
0"
0$
#4245
1"
1$
b10101111 (
#4250
0"
0$
#4255
1"
1$
b10110000 (
#4260
0"
0$
#4265
1"
1$
b10110001 (
#4270
0"
0$
#4275
1"
1$
b10110010 (
#4280
0"
0$
#4285
1"
1$
b10110011 (
#4290
0"
0$
#4295
1"
1$
b10110100 (
#4300
0"
0$
#4305
1"
1$
b10110101 (
#4310
0"
0$
#4315
1"
1$
b10110110 (
#4320
0"
0$
#4325
1"
1$
b10110111 (
#4330
0"
0$
#4335
1"
1$
b10111000 (
#4340
0"
0$
#4345
1"
1$
b10111001 (
#4350
0"
0$
#4355
1"
1$
b10111010 (
#4360
0"
0$
#4365
1"
1$
b10111011 (
#4370
0"
0$
#4375
1"
1$
b10111100 (
#4380
0"
0$
#4385
1"
1$
b10111101 (
#4390
0"
0$
#4395
1"
1$
b10111110 (
#4400
0"
0$
#4405
1"
1$
b10111111 (
#4410
0"
0$
#4415
1"
1$
b11000000 (
#4420
0"
0$
#4425
1"
1$
b11000001 (
#4430
0"
0$
#4435
1"
1$
b11000010 (
#4440
0"
0$
#4445
1"
1$
b11000011 (
#4450
0"
0$
#4455
1"
1$
b11000100 (
#4460
0"
0$
#4465
1"
1$
b11000101 (
#4470
0"
0$
#4475
1"
1$
b11000110 (
#4480
0"
0$
#4485
1"
1$
b11000111 (
#4490
0"
0$
#4495
1"
1$
b11001000 (
#4500
0"
0$
#4505
1"
1$
b11001001 (
#4510
0"
0$
#4515
1"
1$
b11001010 (
#4520
0"
0$
#4525
1"
1$
b11001011 (
#4530
0"
0$
#4535
1"
1$
b11001100 (
#4540
0"
0$
#4545
1"
1$
b11001101 (
#4550
0"
0$
#4555
1"
1$
b11001110 (
#4560
0"
0$
#4565
1"
1$
b11001111 (
#4570
0"
0$
#4575
1"
1$
b11010000 (
#4580
0"
0$
#4585
1"
1$
b11010001 (
#4590
0"
0$
#4595
1"
1$
b11010010 (
#4600
0"
0$
#4605
1"
1$
b11010011 (
#4610
0"
0$
#4615
1"
1$
b11010100 (
#4620
0"
0$
#4625
1"
1$
b11010101 (
#4630
0"
0$
#4635
1"
1$
b11010110 (
#4640
0"
0$
#4645
1"
1$
b11010111 (
#4650
0"
0$
#4655
1"
1$
b11011000 (
#4660
0"
0$
#4665
1"
1$
b11011001 (
#4670
0"
0$
#4675
1"
1$
b11011010 (
#4680
0"
0$
#4685
1"
1$
b11011011 (
#4690
0"
0$
#4695
1"
1$
b11011100 (
#4700
0"
0$
#4705
1"
1$
b11011101 (
#4710
0"
0$
#4715
1"
1$
b11011110 (
#4720
0"
0$
#4725
1"
1$
b11011111 (
#4730
0"
0$
#4735
1"
1$
b11100000 (
#4740
0"
0$
#4745
1"
1$
b11100001 (
#4750
0"
0$
#4755
1"
1$
b11100010 (
#4760
0"
0$
#4765
1"
1$
b11100011 (
#4770
0"
0$
#4775
1"
1$
b11100100 (
#4780
0"
0$
#4785
1"
1$
b11100101 (
#4790
0"
0$
#4795
1"
1$
b11100110 (
#4800
0"
0$
#4805
1"
1$
b11100111 (
#4810
0"
0$
#4815
1"
1$
b11101000 (
#4820
0"
0$
#4825
1"
1$
b11101001 (
#4830
0"
0$
#4835
1"
1$
b11101010 (
#4840
0"
0$
#4845
1"
1$
b11101011 (
#4850
0"
0$
#4855
1"
1$
b11101100 (
#4860
0"
0$
#4865
1"
1$
b11101101 (
#4870
0"
0$
#4875
1"
1$
b11101110 (
#4880
0"
0$
#4885
1"
1$
b11101111 (
#4890
0"
0$
#4895
1"
1$
b11110000 (
#4900
0"
0$
#4905
1"
1$
b11110001 (
#4910
0"
0$
#4915
1"
1$
b11110010 (
#4920
0"
0$
#4925
1"
1$
b11110011 (
#4930
0"
0$
#4935
1"
1$
b11110100 (
#4940
0"
0$
#4945
1"
1$
b11110101 (
#4950
0"
0$
#4955
1"
1$
b11110110 (
#4960
0"
0$
#4965
1"
1$
b11110111 (
#4970
0"
0$
#4975
1"
1$
b11111000 (
#4980
0"
0$
#4985
1"
1$
b11111001 (
1&
#4990
0"
0$
#4995
1"
1$
b0 (
0'
0&
0!
#5000
0"
0$
#5005
1"
1$
b1 (
#5010
0"
0$
#5015
1"
1$
b10 (
#5020
0"
0$
#5025
1"
1$
b11 (
#5030
0"
0$
#5035
1"
1$
b100 (
#5040
0"
0$
#5045
1"
1$
b101 (
#5050
0"
0$
#5055
1"
1$
b110 (
#5060
0"
0$
#5065
1"
1$
b111 (
#5070
0"
0$
#5075
1"
1$
b1000 (
#5080
0"
0$
#5085
1"
1$
b1001 (
#5090
0"
0$
#5095
1"
1$
b1010 (
#5100
0"
0$
#5105
1"
1$
b1011 (
#5110
0"
0$
#5115
1"
1$
b1100 (
#5120
0"
0$
#5125
1"
1$
b1101 (
#5130
0"
0$
#5135
1"
1$
b1110 (
#5140
0"
0$
#5145
1"
1$
b1111 (
#5150
0"
0$
#5155
1"
1$
b10000 (
#5160
0"
0$
#5165
1"
1$
b10001 (
#5170
0"
0$
#5175
1"
1$
b10010 (
#5180
0"
0$
#5185
1"
1$
b10011 (
#5190
0"
0$
#5195
1"
1$
b10100 (
#5200
0"
0$
#5205
1"
1$
b10101 (
#5210
0"
0$
#5215
1"
1$
b10110 (
#5220
0"
0$
#5225
1"
1$
b10111 (
#5230
0"
0$
#5235
1"
1$
b11000 (
#5240
0"
0$
#5245
1"
1$
b11001 (
#5250
0"
0$
#5255
1"
1$
b11010 (
#5260
0"
0$
#5265
1"
1$
b11011 (
#5270
0"
0$
#5275
1"
1$
b11100 (
#5280
0"
0$
#5285
1"
1$
b11101 (
#5290
0"
0$
#5295
1"
1$
b11110 (
