DAY_16/design.sv
// Code your design here
`timescale 10ns/1ps

module bcd_2_xs3(input [3:0] bcd,
                 output reg [3:0] xs
                );
  
  always@(bcd)
    begin
      xs[0]= ~ bcd[0];
      xs[1]= ~(bcd[0] ^ bcd[1]);
      xs[2]= (~ bcd[2] & bcd[1]) |  (~ bcd[2] & bcd[0]) | (~ bcd[0] & bcd[2] & ~bcd[1]);
      xs[3]= bcd[3] | (bcd[2] & bcd[1]) | (bcd[2] & bcd[0]);
    end
  
endmodule

DAY_16/testbench.sv
// Code your testbench here
// or browse Examples
`timescale 10ns/1ps


module bcd_2_xs3_tb;
  
  wire [3:0] xs;
  reg [3:0] bcd;

  bcd_2_xs3 DUT(.bcd(bcd),.xs(xs));
  
  
  initial 
    begin
      $dumpfile("dump.vcd");
      $dumpvars;
    end
 
  initial 
    begin
           #10   bcd=4'b0000;
	       #10   bcd=4'b0001;
	       #10   bcd=4'b0010;
	       #10   bcd=4'b0011;
	       #10   bcd=4'b0100;
	       #10   bcd=4'b0101;
	       #10   bcd=4'b0110;
	       #10   bcd=4'b0111;
	       #10   bcd=4'b1000;
	       #10   bcd=4'b1001;
	       #10   bcd=4'b1010;
	       #10   bcd=4'b1011;
	       #10   bcd=4'b1100;
	       #10   bcd=4'b1101;
	       #10   bcd=4'b1110;
	       #10   bcd=4'b1111;
    
  end
   
endmodule

DAY_16/dump.vcd
$date
	Fri May 12 04:08:01 2023
$end
$version
	Icarus Verilog
$end
$timescale
	1ps
$end
$scope module bcd_2_xs3_tb $end
$var wire 4 ! xs [3:0] $end
$var reg 4 " bcd [3:0] $end
$scope module DUT $end
$var wire 4 # bcd [3:0] $end
$var reg 4 $ xs [3:0] $end
$upscope $end
$upscope $end
$enddefinitions $end
#0
$dumpvars
bx $
bx #
bx "
bx !
$end
#100000
b11 $
b11 !
b0 "
b0 #
#200000
b100 $
b100 !
b1 "
b1 #
#300000
b101 $
b101 !
b10 "
b10 #
#400000
b110 $
b110 !
b11 "
b11 #
#500000
b111 $
b111 !
b100 "
b100 #
#600000
b1000 $
b1000 !
b101 "
b101 #
#700000
b1001 $
b1001 !
b110 "
b110 #
#800000
b1010 $
b1010 !
b111 "
b111 #
#900000
b1011 $
b1011 !
b1000 "
b1000 #
#1000000
b1100 $
b1100 !
b1001 "
b1001 #
#1100000
b1101 $
b1101 !
b1010 "
b1010 #
#1200000
b1110 $
b1110 !
b1011 "
b1011 #
#1300000
b1111 $
b1111 !
b1100 "
b1100 #
#1400000
b1000 $
b1000 !
b1101 "
b1101 #
#1500000
b1001 $
b1001 !
b1110 "
b1110 #
#1600000
b1010 $
b1010 !
b1111 "
b1111 #
