DAY_32/JOHNSHON_COUNTER/design.sv
 module johnson_counter(
	    				input clk,
	   					input reset,
	    				output reg [3:0] out
					);
	
always @(posedge clk) 
     begin
       if (!reset) 
          begin
	        out <= 4'b0000;// since its a self starting counter
	      end 
       else 
         begin
           out <= {~out[0],out[3:1]}; //OUTPUT OF NTH FF IS INVERTED AND FEDBACK TO FIRST FF
	    end
	end

endmodule


// mod number = 2n
// maximum count = 2^(n)-1
// output frequency =  fclk/mod_number --> fclk/2n

DAY_32/JOHNSHON_COUNTER/testbench.sv
module johnson_counter_tb;
 
  reg clk;
  reg reset;
  wire [3:0] out;
	    
  johnson_counter DUT(.clk(clk), 
                   .reset(reset), 
                   .out(out)
                  );
	
always #10 clk = ~clk;
  
initial 
  begin
    clk = 0;
    
    $dumpfile("dump.vcd");
    $dumpvars;
    
    reset = 0;
    
    #50 reset = 1;

   #300 $finish;
	    
  end

endmodule

DAY_32/JOHNSHON_COUNTER/dump.vcd
$date
	Sun Jun 11 06:31:53 2023
$end
$version
	Icarus Verilog
$end
$timescale
	1s
$end
$scope module johnson_counter_tb $end
$var wire 4 ! out [3:0] $end
$var reg 1 " clk $end
$var reg 1 # reset $end
$scope module DUT $end
$var wire 1 $ clk $end
$var wire 1 % reset $end
$var reg 4 & out [3:0] $end
$upscope $end
$upscope $end
$enddefinitions $end
#0
$dumpvars
bx &
0%
0$
0#
0"
bx !
$end
#10
b0 &
b0 !
1"
1$
#20
0"
0$
#30
1"
1$
#40
0"
0$
#50
b1000 &
b1000 !
1"
1$
1#
1%
#60
0"
0$
#70
b1100 &
b1100 !
1"
1$
#80
0"
0$
#90
b1110 &
b1110 !
1"
1$
#100
0"
0$
#110
b1111 &
b1111 !
1"
1$
#120
0"
0$
#130
b111 &
b111 !
1"
1$
#140
0"
0$
#150
b11 &
b11 !
1"
1$
#160
0"
0$
#170
b1 &
b1 !
1"
1$
#180
0"
0$
#190
b0 &
b0 !
1"
1$
#200
0"
0$
#210
b1000 &
b1000 !
1"
1$
#220
0"
0$
#230
b1100 &
b1100 !
1"
1$
#240
0"
0$
#250
b1110 &
b1110 !
1"
1$
#260
0"
0$
#270
b1111 &
b1111 !
1"
1$
#280
0"
0$
#290
b111 &
b111 !
1"
1$
#300
0"
0$
#310
b11 &
b11 !
1"
1$
#320
0"
0$
#330
b1 &
b1 !
1"
1$
#340
0"
0$
#350
b0 &
b0 !
1"
1$
