DAY_8/design.sv
`timescale 1ns/1ps

module BCD_ADDER(a,b,c_in,sum,carry); //behaviroal modellling
    input [3:0] a,b;
    input c_in;
  
    output [3:0] sum;
    output carry;
    
  reg [4:0] sum_temp; //5-bit temp storing of sum before +6 correction
  reg [3:0] sum;  //final sum variable
    reg carry;  

    always @(a,b,c_in)
      begin
          sum_temp = a+b+c_in; 
          if(sum_temp > 9)    begin
              sum_temp = sum_temp+6; //addition of 6 if the result is > than 9
              carry = 1;  //Correction bit setting
              sum = sum_temp[3:0]; 
      end
        else   
          begin
            carry = 0;
            sum = sum_temp[3:0];
        end
    end     
endmodule

DAY_8/testbench.sv
`timescale 1ns/1ps

module BCD_ADDER_TB;
  
    // Inputs
    reg [3:0] a;
    reg [3:0] b;
    reg c_in;
  
    // Outputs
    wire [3:0] sum;
    wire carry;

    BCD_ADDER DUT(
        .a(a), 
        .b(b), 
        .c_in(c_in), 
        .sum(sum), 
        .carry(carry)
    );

    initial 
      begin
        $dumpfile("waveform.vcd");
        $dumpvars;
      end 
  
  initial 
    begin 
        a = 0;  b = 0;  c_in = 0;   #100;
        a = 4;  b = 8;  c_in = 1;   #100;
        a = 4;  b = 1;  c_in = 0;   #100;
        a = 6;  b = 9;  c_in = 1;   #100;
        a = 6;  b = 9;  c_in = 0;   #100;
        a = 8;  b = 2;  c_in = 0;   #100;
        a = 8;  b = 2;  c_in = 1;   #100;
        a = 9;  b = 9;  c_in = 1;   #100;
   
    end
     
endmodule

DAY_8/waveform.vcd
$date
	Sat Apr 29 05:24:01 2023
$end
$version
	Icarus Verilog
$end
$timescale
	1ps
$end
$scope module BCD_ADDER_TB $end
$var wire 1 ! carry $end
$var wire 4 " sum [3:0] $end
$var reg 4 # a [3:0] $end
$var reg 4 $ b [3:0] $end
$var reg 1 % c_in $end
$scope module DUT $end
$var wire 4 & a [3:0] $end
$var wire 4 ' b [3:0] $end
$var wire 1 ( c_in $end
$var reg 1 ) carry $end
$var reg 4 * sum [3:0] $end
$var reg 5 + sum_temp [4:0] $end
$upscope $end
$upscope $end
$enddefinitions $end
#0
$dumpvars
b0 +
b0 *
0)
0(
b0 '
b0 &
0%
b0 $
b0 #
b0 "
0!
$end
#100000
b11 *
b11 "
1)
1!
b10011 +
1%
1(
b1000 $
b1000 '
b100 #
b100 &
#200000
b101 *
b101 "
0)
0!
b101 +
0%
0(
b1 $
b1 '
#300000
b110 *
b110 "
1)
1!
b10110 +
1%
1(
b1001 $
b1001 '
b110 #
b110 &
#400000
b101 *
b101 "
b10101 +
0%
0(
#500000
b0 *
b0 "
b10000 +
b10 $
b10 '
b1000 #
b1000 &
#600000
b1 *
b1 "
b10001 +
1%
1(
#700000
b1001 *
b1001 "
b11001 +
b1001 $
b1001 '
b1001 #
b1001 &
