DAY_47/design.sv
module seq_non_overlap(input clk, reset, data_stream,
                       output mealy_output);
  
  
//1010 non overlapping sequence detector 
  
localparam A=1,B=2,C=3,D=4;  
reg [3:0] present_state, next_state;
  
  
  //dff block
  
  always @(posedge clk) 
    begin
    if(!reset) 
      present_state <= A;
    else 
      present_state <= next_state;
    end
  
  
  //combinational block
  
  always @(present_state or data_stream) 
    begin
      case(present_state)
        A: begin
             if(data_stream == 0) 
               next_state = A;
             else       
               next_state = B;
           end
        
        B: begin
             if(data_stream == 0) 
               next_state = C;
             else       
               next_state = B;
           end
        
        C: begin
             if(data_stream == 0) 
               next_state = A;
             else       
               next_state = D;
           end
        
        D: begin
          if(data_stream == 0) 
            next_state = A; 
             else       
               next_state = B;
           end
        
        default: next_state = A;
      endcase
  	end
  
  assign mealy_output = (present_state == D)? 1:0;
  
endmodule

DAY_47/testbench.sv
module seq_non_overlap_tb;
  
  
reg clk,reset,data_stream;
wire mealy_output;
  
seq_non_overlap DUT(clk,reset,data_stream,mealy_output);
  
initial 
  begin 
    $dumpfile("dump.vcd");
    $dumpvars;
  end

  always #5 clk= ~clk;
  
  initial
    begin
      clk=0;
      reset=1;
      data_stream=0;
      #10;
      #20 reset = 0;
      #5 reset  = 1;
       #10 data_stream = 0;
      #10 data_stream = 1;
      #10 data_stream = 0;
      #10 data_stream = 1;
      #10 data_stream = 0;
      #10 data_stream = 1;
      #10 data_stream = 0;
      #10 data_stream = 1;
      #10 data_stream = 1;
      #10 data_stream = 1;
      #10 data_stream = 0;
      #50 $finish;
  end
endmodule

DAY_47/dump.vcd
$date
	Wed Jul  5 16:47:48 2023
$end
$version
	Icarus Verilog
$end
$timescale
	1s
$end
$scope module seq_non_overlap_tb $end
$var wire 1 ! mealy_output $end
$var reg 1 " clk $end
$var reg 1 # data_stream $end
$var reg 1 $ reset $end
$scope module DUT $end
$var wire 1 % clk $end
$var wire 1 & data_stream $end
$var wire 1 ! mealy_output $end
$var wire 1 ' reset $end
$var reg 4 ( next_state [3:0] $end
$var reg 4 ) present_state [3:0] $end
$upscope $end
$upscope $end
$enddefinitions $end
#0
$dumpvars
bx )
b1 (
1'
0&
0%
1$
0#
0"
x!
$end
#5
0!
b1 )
1"
1%
#10
0"
0%
#15
1"
1%
#20
0"
0%
#25
1"
1%
#30
0"
0%
0$
0'
#35
1"
1%
1$
1'
#40
0"
0%
#45
b10 )
b10 (
1"
1%
1#
1&
#50
0"
0%
#55
1"
1%
#60
0"
0%
#65
b11 )
b1 (
1"
1%
0#
0&
#70
0"
0%
#75
1!
b100 )
b10 (
1"
1%
1#
1&
#80
0"
0%
#85
0!
b1 )
b1 (
1"
1%
0#
0&
#90
0"
0%
#95
b10 )
b10 (
1"
1%
1#
1&
#100
0"
0%
#105
b11 )
b1 (
1"
1%
0#
0&
#110
0"
0%
#115
1!
b100 )
b10 (
1"
1%
1#
1&
#120
0"
0%
#125
0!
b1 )
b1 (
1"
1%
0#
0&
#130
0"
0%
#135
b10 )
b10 (
1"
1%
1#
1&
#140
0"
0%
#145
b11 )
b1 (
1"
1%
0#
0&
#150
0"
0%
#155
b1 )
1"
1%
