DAY_39/design.sv
module UNI_SR(input clk,clear,
              input [3:0]data_in,
              input shift_data,
              input [1:0]mode,
              output reg [3:0] data_out,
              output leftshift_o,rightshift_o
             );
  
  
//data_in AND data_out are parallel data 
//shift_data is a 1bit data to be shifted by one bit to the left or right 
  
  always@(posedge clk)
    begin
      if(clear)
        data_out <= 0;
      else
        begin
          case(mode)
            
            2'b01 : data_out <= {shift_data,data_out[3:1]}; //right shift
            2'b10 : data_out <= {data_out[2:0],shift_data};  //left shift
            2'b11 : data_out <= data_in;
            default: data_out <= data_out;
        
          endcase  
        end
     end
  assign leftshift_o = data_out[0];
  assign rightshift_o = data_out[3];
      
      
endmodule

DAY_39/testbench.sv
module UNI_SR_TB;
  
  reg clk,clear,shift_data;
  reg [1:0] mode;
  reg [3:0] data_in;
  wire [3:0] data_out;
  wire leftshift_o,rightshift_o;
  
  UNI_SR  DUT(clk,clear,
              data_in,shift_data,
              mode,
              data_out,
              leftshift_o,rightshift_o);
  
  always #5 clk = ~clk;
  
  initial 
    begin
    clk=0;
    clear = 1;
    #5 clear =0;
    
    data_in = 4'b1010;
    shift_data = 1'b0;
    
    mode = 2'h3; 
    #5;
    mode = 2'h1; 
    #20;
      
  
    data_in = 4'b1101;
    shift_data = 1'b1;
    mode = 2'h3;
    #10;
    mode = 2'h2; 
    #20;
    mode = 2'h0;
    #10;

   data_in = 4'b0110;
   shift_data = 1'b1;
    mode = 2'h2; 
    #5;
    mode = 2'h1; 
    #20;

    $finish;
  end

  initial
    begin 
    $dumpfile("dump.vcd"); 
    $dumpvars;
  end
   
endmodule

DAY_39/dump.vcd
$date
	Wed Jun 21 04:07:58 2023
$end
$version
	Icarus Verilog
$end
$timescale
	1s
$end
$scope module UNI_SR_TB $end
$var wire 4 ! data_out [3:0] $end
$var wire 1 " leftshift_o $end
$var wire 1 # rightshift_o $end
$var reg 1 $ clear $end
$var reg 1 % clk $end
$var reg 4 & data_in [3:0] $end
$var reg 2 ' mode [1:0] $end
$var reg 1 ( shift_data $end
$scope module DUT $end
$var wire 1 ) clear $end
$var wire 1 * clk $end
$var wire 4 + data_in [3:0] $end
$var wire 1 " leftshift_o $end
$var wire 2 , mode [1:0] $end
$var wire 1 # rightshift_o $end
$var wire 1 - shift_data $end
$var reg 4 . data_out [3:0] $end
$upscope $end
$upscope $end
$enddefinitions $end
#0
$dumpvars
bx .
x-
bx ,
bx +
0*
1)
x(
bx '
bx &
0%
1$
x#
x"
bx !
$end
#5
0"
1#
b1010 .
b1010 !
b11 '
b11 ,
0(
0-
b1010 &
b1010 +
0$
0)
1%
1*
#10
b1 '
b1 ,
0%
0*
#15
1"
0#
b101 .
b101 !
1%
1*
#20
0%
0*
#25
0"
b10 .
b10 !
1%
1*
#30
0%
0*
b11 '
b11 ,
1(
1-
b1101 &
b1101 +
#35
1"
1#
b1101 .
b1101 !
1%
1*
#40
0%
0*
b10 '
b10 ,
#45
b1011 .
b1011 !
1%
1*
#50
0%
0*
#55
0#
b111 .
b111 !
1%
1*
#60
0%
0*
b0 '
b0 ,
#65
1%
1*
#70
0%
0*
b10 '
b10 ,
b110 &
b110 +
#75
1#
b1011 .
b1011 !
1%
1*
b1 '
b1 ,
#80
0%
0*
#85
b1101 .
b1101 !
1%
1*
#90
0%
0*
#95
0"
b1110 .
b1110 !
1%
1*
