DAY_45/design.sv
module RISING_edge_FSM(
                            input wire clk, reset, 
                            input wire level, 
                            output reg MEALY_OUTPUT
                            );

localparam  S0 = 1'b0, S1 =  1'b1; // ONLY 2 states are required for Mealy FSM

reg Mealy_Present, Mealy_next; 

// MODELLING OF D FF OR THE SEQUENTIAL BLOCK
  
always @(posedge clk, posedge reset)
begin
    if(reset) 
        Mealy_Present <= S0;
    else 
        Mealy_Present <= Mealy_next;
end

//MODELLING THE STATES OR THE COMBINATIONAL BLOCK
  
always @(Mealy_Present, level)		//HERE LEVEL IS THE I/P (INSTEAD OF A CLOCK FOR EDGEDETECTION)
	begin
      // store present state as next
      Mealy_next = Mealy_Present; 
      MEALY_OUTPUT = 1'b0;
      // set tick to zero (so that 'tick = 1' is available for 1 cycle only)
      case(Mealy_Present)
          S0: if(level)  
            begin 
              // if level is 1, then go to state one,
              Mealy_next = S1; 
              // otherwise remain in same state.
              MEALY_OUTPUT = 1'b1;
            end
          S1: 
            if(!level) 
                // if level is 0, then go to zero state,
                  Mealy_next = S0; 
        // otherwise remain in one state.
        default :  MEALY_OUTPUT = 1'b0; 
     endcase
end
endmodule

DAY_45/testbench.sv
module RISING_edge_FSM_TB;
  
reg clk,reset,level;
wire MEALY_OUTPUT;
  

  RISING_edge_FSM DUT(clk,reset,level,MEALY_OUTPUT);
  
  
always #5 clk = ~clk;
  
initial 
  begin 
    $dumpfile("dump.vcd");
    $dumpvars;
    clk=0;
    reset=0;
    #20; 
    reset=1;
    #5;
    #50 level = 1;
    #50 level = 0;
    #20 level = 1;
    #10 level = 0;
    #12 level = 1;
    #11 level = 0;
    #100 $finish;
  end
  
endmodule

DAY_45/dump.vcd
$date
	Mon Jul  3 14:24:11 2023
$end
$version
	Icarus Verilog
$end
$timescale
	1s
$end
$scope module RISING_edge_FSM_TB $end
$var wire 1 ! MEALY_OUTPUT $end
$var reg 1 " clk $end
$var reg 1 # level $end
$var reg 1 $ reset $end
$scope module DUT $end
$var wire 1 % clk $end
$var wire 1 & level $end
$var wire 1 ' reset $end
$var reg 1 ( MEALY_OUTPUT $end
$var reg 1 ) Mealy_Present $end
$var reg 1 * Mealy_next $end
$upscope $end
$upscope $end
$enddefinitions $end
#0
$dumpvars
x*
x)
x(
0'
x&
0%
0$
x#
0"
x!
$end
#5
1"
1%
#10
0"
0%
#15
1"
1%
#20
0(
0!
0*
0)
0"
0%
1$
1'
#25
1"
1%
#30
0"
0%
#35
1"
1%
#40
0"
0%
#45
1"
1%
#50
0"
0%
#55
1"
1%
#60
0"
0%
#65
1"
1%
#70
0"
0%
#75
1(
1!
1*
1"
1%
1#
1&
#80
0"
0%
#85
1"
1%
#90
0"
0%
#95
1"
1%
#100
0"
0%
#105
1"
1%
#110
0"
0%
#115
1"
1%
#120
0"
0%
#125
0(
0!
0*
1"
1%
0#
0&
#130
0"
0%
#135
1"
1%
#140
0"
0%
#145
1(
1!
1*
1"
1%
1#
1&
#150
0"
0%
#155
0(
0!
0*
1"
1%
0#
0&
#160
0"
0%
#165
1"
1%
#167
1(
1!
1*
1#
1&
#170
0"
0%
#175
1"
1%
#178
0(
0!
0*
0#
0&
